jm_networking/__init__.py
jm_networking/network.py
jm_networking-1.0.17.dist-info/METADATA
jm_networking-1.0.17.dist-info/RECORD
jm_networking-1.0.17.dist-info/WHEEL
jm_networking-1.0.17.dist-info/top_level.txt
